dpe/__init__.py
dpe/core.py
dpe/datasets.py
dpe/eval_helpers.py
dpe/isomaxplus.py
dpe/misc.py
dpe/plot_helpers.py
dpe-0.2.0.dist-info/licenses/LICENSE
dpe-0.2.0.dist-info/METADATA
dpe-0.2.0.dist-info/WHEEL
dpe-0.2.0.dist-info/top_level.txt
dpe-0.2.0.dist-info/RECORD
