Metadata-Version: 2.4
Name: dpe
Version: 0.2.0
Summary: Diverse Prototypical Ensembles Improve Robustness to Subpopulation Shift
Author-email: Minh To <tnnhatminh@gmail.com>
License-Expression: MIT
Project-URL: Homepage, https://github.com/minhto2802/dpe4subpop
Requires-Python: >=3.7
License-File: LICENSE
Requires-Dist: torch>=1.9
Requires-Dist: numpy
Requires-Dist: scikit-learn
Dynamic: license-file
